docs/.gitignore
docs/Makefile
docs/cli_usage.rst
docs/conf.py
docs/features.rst
docs/index.rst
docs/install.rst
docs/make.sh
docs/requirements.txt
docs/style_guide.py
docs/upload.sh
docs/_templates/layout.html
docs/api/modules.rst
figures/QSPRpred_logo.jpg
figures/QSPRpred_workflow.png
qsprpred/__init__.py
qsprpred/_version.py
qsprpred/data_CLI.py
qsprpred/model_CLI.py
qsprpred/predict_CLI.py
qsprpred/tasks.py
qsprpred/benchmarks/__init__.py
qsprpred/benchmarks/replica.py
qsprpred/benchmarks/runner.py
qsprpred/benchmarks/tests.py
qsprpred/benchmarks/settings/__init__.py
qsprpred/benchmarks/settings/benchmark.py
qsprpred/benchmarks/settings/data_prep.py
qsprpred/data/__init__.py
qsprpred/data/chem/__init__.py
qsprpred/data/chem/clustering.py
qsprpred/data/chem/matching.py
qsprpred/data/chem/scaffolds.py
qsprpred/data/chem/standardization.py
qsprpred/data/chem/tests.py
qsprpred/data/descriptors/__init__.py
qsprpred/data/descriptors/fingerprints.py
qsprpred/data/descriptors/sets.py
qsprpred/data/descriptors/tests.py
qsprpred/data/processing/__init__.py
qsprpred/data/processing/applicability_domain.py
qsprpred/data/processing/data_filters.py
qsprpred/data/processing/feature_filters.py
qsprpred/data/processing/feature_standardizers.py
qsprpred/data/processing/mol_processor.py
qsprpred/data/processing/tests.py
qsprpred/data/sampling/__init__.py
qsprpred/data/sampling/folds.py
qsprpred/data/sampling/splits.py
qsprpred/data/sampling/tests.py
qsprpred/data/sources/__init__.py
qsprpred/data/sources/data_source.py
qsprpred/data/sources/papyrus/__init__.py
qsprpred/data/sources/papyrus/papyrus_class.py
qsprpred/data/sources/papyrus/papyrus_filter.py
qsprpred/data/tables/__init__.py
qsprpred/data/tables/base.py
qsprpred/data/tables/mol.py
qsprpred/data/tables/pandas.py
qsprpred/data/tables/qspr.py
qsprpred/data/tables/searchable.py
qsprpred/data/tables/tests.py
qsprpred/extra/__init__.py
qsprpred/extra/data/__init__.py
qsprpred/extra/data/descriptors/__init__.py
qsprpred-3.2.1.dist-info/LICENSE
qsprpred-3.2.1.dist-info/METADATA
qsprpred-3.2.1.dist-info/WHEEL
qsprpred-3.2.1.dist-info/top_level.txt
qsprpred-3.2.1.dist-info/RECORD
