Metadata-Version: 2.1
Name: qsprpred
Version: 3.2.1
Summary: A cheminformatics package for training and testing QSAR/QSPR models
Author-email: Helle van den Maagdenberg <h.w.van.den.maagdenberg@lacdr.leidenuniv.nl>, Linde Schoenmaker <l.schoenmaker@lacdr.leidenuniv.nl>, Martin Sicho <m.sicho@lacdr.leidenuniv.nl>, David Araripe <d.figueiredo.vidal@lacdr.leidenuniv.nl>, Sohvi Luukkonen <s.luukkonen@lacdr.leidenuniv.nl>, Olivier Béquignon <o.j.m.bequignon@lacdr.leidenuniv.nl>, Marina Gorostiola Gonzalez <m.gorostiola.gonzalez@lacdr.leidenuniv.nl>, Remco van den Broek <r.l.van.den.broek@umail.leidenuniv.nl>, Gerard van Westen
Maintainer-email: Helle van den Maagdenberg <h.w.van.den.maagdenberg@lacdr.leidenuniv.nl>, Linde Schoenmaker <l.schoenmaker@lacdr.leidenuniv.nl>, Martin Sicho <m.sicho@lacdr.leidenuniv.nl>, David Araripe <d.figueiredo.vidal@lacdr.leidenuniv.nl>, Sohvi Luukkonen <s.luukkonen@lacdr.leidenuniv.nl>, Olivier Béquignon <o.j.m.bequignon@lacdr.leidenuniv.nl>, Marina Gorostiola Gonzalez <m.gorostiola.gonzalez@lacdr.leidenuniv.nl>, Remco van den Broek <r.l.van.den.broek@umail.leidenuniv.nl>, Gerard van We
License: MIT License
Project-URL: homepage, https://github.com/CDDLeiden/QSPRpred
Project-URL: repository, https://github.com/CDDLeiden/QSPRpred
Project-URL: documentation, https://cddleiden.github.io/QSPRpred/docs/
Keywords: qsar,machine learning,cheminformatics
Classifier: Development Status :: 4 - Beta
Classifier: Operating System :: OS Independent
Classifier: Programming Language :: Python
Classifier: Programming Language :: Python :: 3.10
Classifier: Programming Language :: Python :: 3.11
Classifier: Programming Language :: Python :: 3.12
Classifier: Programming Language :: Python :: 3 :: Only
Classifier: Topic :: Scientific/Engineering :: Bio-Informatics
Classifier: Topic :: Scientific/Engineering :: Chemistry
Requires-Python: >=3.10
License-File: LICENSE
Requires-Dist: parameterized
Requires-Dist: pebble
Requires-Dist: numpy
Requires-Dist: scikit-learn >=1.0.2
Requires-Dist: pandas >=1.2.2
Requires-Dist: matplotlib >=2.0
Requires-Dist: chembl-structure-pipeline >=1.2.0
Requires-Dist: rdkit
Requires-Dist: optuna
Requires-Dist: gitpython
Requires-Dist: xgboost
Requires-Dist: boruta
Requires-Dist: tqdm
Requires-Dist: ml2json
Requires-Dist: jsonpickle
Requires-Dist: papyrus-scripts
Requires-Dist: gbmtsplits
Requires-Dist: mlchemad
Requires-Dist: mols2grid
Provides-Extra: chemprop
Requires-Dist: rdkit <2023.9.6 ; extra == 'chemprop'
Requires-Dist: chemprop <2.0.0,>=1.6.0 ; extra == 'chemprop'
Provides-Extra: deep
Requires-Dist: torch >=1.7.0 ; extra == 'deep'
Provides-Extra: dev
Requires-Dist: qsprpred[full] ; extra == 'dev'
Requires-Dist: pre-commit ; extra == 'dev'
Requires-Dist: isort ; extra == 'dev'
Requires-Dist: yapf ; extra == 'dev'
Requires-Dist: ruff ; extra == 'dev'
Requires-Dist: pytest ; extra == 'dev'
Provides-Extra: extra
Requires-Dist: mold2-pywrapper ; extra == 'extra'
Requires-Dist: dask[distributed] ; extra == 'extra'
Requires-Dist: padel-pywrapper >=1.0.2.post1 ; extra == 'extra'
Requires-Dist: Mordred ; extra == 'extra'
Requires-Dist: biopython ; extra == 'extra'
Requires-Dist: prodec ; extra == 'extra'
Requires-Dist: Signature-pywrapper ; extra == 'extra'
Provides-Extra: full
Requires-Dist: qsprpred[deep] ; extra == 'full'
Requires-Dist: qsprpred[extra] ; extra == 'full'
Requires-Dist: qsprpred[chemprop] ; extra == 'full'
